Codes_package/Gaus.py
Codes_package/__init__.py
Codes_package/morse.py
morse_and_gau_codes-0.1.1.dist-info/LICENSE
morse_and_gau_codes-0.1.1.dist-info/METADATA
morse_and_gau_codes-0.1.1.dist-info/WHEEL
morse_and_gau_codes-0.1.1.dist-info/top_level.txt
morse_and_gau_codes-0.1.1.dist-info/RECORD
